nak/__init__.py
nak/command.py
nak/config.py
nak/gateway.py
nak/nak.py
nak/parser.py
nak/settings.py
nak/utils.py
next_app_kit-1.0.4.dist-info/licenses/LICENSE
tests/__init__.py
tests/test_command.py
tests/test_conf.py
tests/test_gateway.py
tests/test_utils.py
next_app_kit-1.0.4.dist-info/METADATA
next_app_kit-1.0.4.dist-info/WHEEL
next_app_kit-1.0.4.dist-info/entry_points.txt
next_app_kit-1.0.4.dist-info/top_level.txt
next_app_kit-1.0.4.dist-info/RECORD
