Metadata-Version: 2.4
Name: next-app-kit
Version: 1.0.4
Home-page: https://github.com/29next/app-kit
Author: 29next
Author-email: dev@29next.com
Requires-Python: >=3.6
License-File: LICENSE
Requires-Dist: PyYAML>=5.4
Requires-Dist: requests>=2.25
Requires-Dist: python-decouple>=3.6
Dynamic: author
Dynamic: author-email
Dynamic: description
Dynamic: description-content-type
Dynamic: home-page
Dynamic: license-file
Dynamic: requires-dist
Dynamic: requires-python
